neuro_fuzzy/__init__.py
neuro_fuzzy-0.0.0.dist-info/METADATA
neuro_fuzzy-0.0.0.dist-info/WHEEL
neuro_fuzzy-0.0.0.dist-info/RECORD
